SacCkPt/__init__.py
SacCkPt/checkpoint.py
SacCkPt-0.0.3.dist-info/LICENSE
SacCkPt-0.0.3.dist-info/METADATA
SacCkPt-0.0.3.dist-info/WHEEL
SacCkPt-0.0.3.dist-info/top_level.txt
SacCkPt-0.0.3.dist-info/RECORD
