Metadata-Version: 2.1
Name: SacCkPt
Version: 0.0.3
Summary: A Python package to save and load checkpoint data.
Author: Dikshita
Author-email: dikshita.poojari@neosoftmail.com
License-File: LICENSE
Requires-Dist: python-dotenv (==0.21.1)
